webhookit
