Metadata-Version: 1.1
Name: webhookit
Version: 0.0.9
Summary: Bind git webhooks with actions. Simple git webhook cli tool for automation tasks.
Home-page: https://github.com/hustcc
Author: hustcc
Author-email: i@hust.cc
License: MIT
Keywords: webhookit,webhook,github,gitlab,gogs,git-webhook
Platform: UNKNOWN
Classifier: Intended Audience :: Developers
Classifier: Operating System :: OS Independent
Classifier: Natural Language :: Chinese (Simplified)
Classifier: Programming Language :: Python
Classifier: Programming Language :: Python :: 2
Classifier: Programming Language :: Python :: 2.5
Classifier: Programming Language :: Python :: 2.6
Classifier: Programming Language :: Python :: 2.7
Classifier: Programming Language :: Python :: 3
Classifier: Programming Language :: Python :: 3.3
Classifier: Programming Language :: Python :: 3.4
Classifier: Programming Language :: Python :: 3.5
Classifier: Programming Language :: Python :: 3.6
Classifier: Topic :: Utilities
